metronome_pulse_postgres_sqlalchemy/__init__.py
metronome_pulse_postgres_sqlalchemy/connector.py
metronome_pulse_postgres_sqlalchemy/sql_builder.py
metronome_pulse_postgres_sqlalchemy-0.1.0.dist-info/METADATA
metronome_pulse_postgres_sqlalchemy-0.1.0.dist-info/WHEEL
metronome_pulse_postgres_sqlalchemy-0.1.0.dist-info/RECORD
